Metadata-Version: 2.1
Name: odoo14-addon-sale-coupon-domain-product-reward-fixed-price
Version: 14.0.1.0.1.dev5
Summary: Sale Coupon Domain Product Reward Fixed Price
Home-page: https://github.com/OCA/sale-promotion
Author: Ooops, Cetmix, Odoo Community Association (OCA)
Author-email: support@odoo-community.org
License: AGPL-3
Platform: UNKNOWN
Classifier: Programming Language :: Python
Classifier: Framework :: Odoo
Classifier: Framework :: Odoo :: 14.0
Classifier: License :: OSI Approved :: GNU Affero General Public License v3
Requires-Python: >=3.6
Requires-Dist: odoo14-addon-sale-coupon-domain-product-discount
Requires-Dist: odoo14-addon-sale-coupon-reward-fixed-price
Requires-Dist: odoo <14.1dev,>=14.0a
